thc/__init__.py
thc/interfaces.py
thc/thc.py
thc/utils.py
thc/crypto/__init__.py
thc/crypto/elgamal.py
thc/crypto/he1.py
thc/crypto/paillier.py
thc/crypto/rsa.py
thc/crypto/trivial.py
thc/demo/__init__.py
thc/demo/_computations.py
thc/demo/faults.py
thc/demo/evoting/README.md
thc/demo/evoting/__init__.py
thc/demo/evoting/_b64.py
thc/demo/evoting/_cli.py
thc/demo/evoting/_votingclient.py
thc/demo/evoting/_votingserver.py
thc/demo/evoting/client.py
thc/demo/evoting/init-db.sql
thc/demo/evoting/server.py
thc-0.2.4.dist-info/METADATA
thc-0.2.4.dist-info/WHEEL
thc-0.2.4.dist-info/entry_points.txt
thc-0.2.4.dist-info/top_level.txt
thc-0.2.4.dist-info/RECORD
