Metadata-Version: 2.1
Name: thc
Version: 0.2.4
Summary: Trustable homomorphic computation
Home-page: https://pablo.rauzy.name/software.html#thc
Author: Pablo Rauzy
Author-email: pr_NOSPAM@up8.edu
License: GNU AGPL v3+
Platform: UNKNOWN
Requires-Dist: pycryptodomex
Provides-Extra: evoting
Requires-Dist: PyNaCl ; extra == 'evoting'
Requires-Dist: requests ; extra == 'evoting'
